{"cameraMode":{"drawMode":0,"name":"Shaded","section":"Shading Mode"},"sceneLighting":false,"audioPlay":false,"sceneViewState":{"m_AlwaysRefresh":false,"showFog":true,"showSkybox":false,"showFlares":true,"showImageEffects":true,"showParticleSystems":true,"showVisualEffectGraphs":true,"m_FxEnabled":true},"in2DMode":false,"pivot":{"x":0.437544584274292,"y":3.5335745811462404,"z":-25.16480255126953},"rotation":{"x":-0.02230544574558735,"y":-0.7843071818351746,"z":-0.028247278183698655,"w":0.6193282604217529},"size":5.714904308319092,"orthographic":false}